{
  "name": "TouchTracker_Export",
  "duration": 9.226999998092651,
  "touchTrackings": [
    {
      "id": "595213",
      "positions": [
        [
          214,
          460
        ]
      ],
      "speeds": [],
      "directions": [],
      "startTimestamp": 1683562772.832,
      "endTimestamp": 1683562772.893
    },
    {
      "id": "2342721",
      "positions": [
        [
          324,
          731
        ],
        [
          321,
          718
        ],
        [
          321,
          716
        ],
        [
          321,
          713
        ],
        [
          321,
          708
        ],
        [
          324,
          702
        ],
        [
          327,
          695
        ],
        [
          330,
          689
        ],
        [
          331,
          682
        ],
        [
          332,
          676
        ],
        [
          332,
          669
        ],
        [
          332,
          664
        ],
        [
          332,
          658
        ],
        [
          332,
          652
        ],
        [
          333,
          647
        ],
        [
          333,
          642
        ],
        [
          333,
          637
        ],
        [
          335,
          635
        ],
        [
          336,
          635
        ],
        [
          337,
          635
        ]
      ],
      "speeds": [
        82.35598107194407,
        66.66673024501506,
        187.49962002115961,
        294.1183400417935,
        394.60116105770913,
        447.9877088063253,
        419.26189612269343,
        415.9461454297661,
        380.17188770328784,
        411.76567605851085,
        294.1142151912936,
        374.99924004231923,
        352.94200805015214,
        299.9430310357246,
        294.1183400417935,
        312.4993667019327,
        166.37845817190643,
        58.823668008358695,
        58.823668008358695
      ],
      "directions": [
        -1.7975951748487824,
        -1.5707963267948966,
        -1.5707963267948966,
        -1.5707963267948966,
        -1.1071487177940904,
        -1.1659045405098132,
        -1.1071487177940904,
        -1.4288992721907328,
        -1.4056476493802699,
        -1.5707963267948966,
        -1.5707963267948966,
        -1.5707963267948966,
        -1.5707963267948966,
        -1.373400766945016,
        -1.5707963267948966,
        -1.5707963267948966,
        -0.7853981633974483,
        0,
        0
      ],
      "startTimestamp": 1683562767.045,
      "endTimestamp": 1683562767.521
    },
    {
      "id": "4722726",
      "positions": [
        [
          187,
          723
        ]
      ],
      "speeds": [],
      "directions": [],
      "startTimestamp": 1683562770.407,
      "endTimestamp": 1683562770.551
    },
    {
      "id": "6463832",
      "positions": [
        [
          332,
          649
        ]
      ],
      "speeds": [],
      "directions": [],
      "startTimestamp": 1683562765.423,
      "endTimestamp": 1683562765.586
    },
    {
      "id": "9516608",
      "positions": [
        [
          329,
          734
        ]
      ],
      "speeds": [],
      "directions": [],
      "startTimestamp": 1683562781.916,
      "endTimestamp": 1683562782.059
    },
    {
      "id": "9614113",
      "positions": [
        [
          212,
          711
        ],
        [
          210,
          707
        ]
      ],
      "speeds": [
        8.768894193384845
      ],
      "directions": [
        -2.0344439357957027
      ],
      "startTimestamp": 1683562776.077,
      "endTimestamp": 1683562776.638
    },
    {
      "id": "9713113",
      "positions": [
        [
          205,
          566
        ]
      ],
      "speeds": [],
      "directions": [],
      "startTimestamp": 1683562771.13,
      "endTimestamp": 1683562771.236
    },
    {
      "id": "15542577",
      "positions": [
        [
          250,
          653
        ],
        [
          237,
          650
        ],
        [
          235,
          650
        ],
        [
          232,
          650
        ],
        [
          230,
          650
        ],
        [
          228,
          650
        ],
        [
          226,
          650
        ],
        [
          225,
          650
        ],
        [
          223,
          651
        ],
        [
          220,
          653
        ],
        [
          216,
          656
        ],
        [
          212,
          657
        ],
        [
          209,
          658
        ],
        [
          207,
          659
        ],
        [
          204,
          659
        ],
        [
          203,
          659
        ],
        [
          201,
          659
        ],
        [
          200,
          659
        ],
        [
          199,
          659
        ],
        [
          197,
          659
        ],
        [
          196,
          659
        ],
        [
          195,
          659
        ],
        [
          194,
          659
        ],
        [
          193,
          659
        ],
        [
          191,
          659
        ],
        [
          189,
          659
        ],
        [
          187,
          659
        ],
        [
          183,
          659
        ],
        [
          180,
          659
        ],
        [
          175,
          659
        ],
        [
          170,
          659
        ],
        [
          164,
          659
        ],
        [
          159,
          659
        ],
        [
          154,
          659
        ],
        [
          150,
          659
        ],
        [
          147,
          659
        ],
        [
          144,
          659
        ],
        [
          143,
          659
        ],
        [
          142,
          660
        ],
        [
          140,
          662
        ],
        [
          137,
          663
        ],
        [
          135,
          664
        ],
        [
          132,
          665
        ],
        [
          129,
          665
        ],
        [
          125,
          665
        ]
      ],
      "speeds": [
        325.40731860263855,
        181.81559668819628,
        499.99650321862833,
        124.99974668077307,
        117.64733601671739,
        117.64733601671739,
        58.823668008358695,
        139.75396537423114,
        212.09175121500795,
        294.1183400417935,
        242.53619648472935,
        197.6419532276576,
        131.5337203525697,
        176.46852911477617,
        58.823668008358695,
        124.99974668077307,
        58.823668008358695,
        58.823668008358695,
        124.99974668077307,
        58.823668008358695,
        58.823668008358695,
        58.823668008358695,
        30.303037308903853,
        117.64568607651745,
        117.64733601671739,
        124.99974668077307,
        235.29467203343478,
        176.47100402507607,
        312.4993667019327,
        294.1183400417935,
        352.94200805015214,
        294.1183400417935,
        312.4993667019327,
        235.29467203343478,
        176.47100402507607,
        187.49962002115961,
        58.822843038258725,
        83.18922908595322,
        166.37845817190643,
        197.6419532276576,
        131.5337203525697,
        186.01677123199408,
        176.47100402507607,
        235.29467203343478
      ],
      "directions": [
        -2.9147938055359073,
        3.141592653589793,
        3.141592653589793,
        3.141592653589793,
        3.141592653589793,
        3.141592653589793,
        3.141592653589793,
        2.677945044588987,
        2.5535900500422257,
        2.498091544796509,
        2.896613990462929,
        2.819842099193151,
        2.677945044588987,
        3.141592653589793,
        3.141592653589793,
        3.141592653589793,
        3.141592653589793,
        3.141592653589793,
        3.141592653589793,
        3.141592653589793,
        3.141592653589793,
        3.141592653589793,
        3.141592653589793,
        3.141592653589793,
        3.141592653589793,
        3.141592653589793,
        3.141592653589793,
        3.141592653589793,
        3.141592653589793,
        3.141592653589793,
        3.141592653589793,
        3.141592653589793,
        3.141592653589793,
        3.141592653589793,
        3.141592653589793,
        3.141592653589793,
        3.141592653589793,
        2.356194490192345,
        2.356194490192345,
        2.819842099193151,
        2.677945044588987,
        2.819842099193151,
        3.141592653589793,
        3.141592653589793
      ],
      "startTimestamp": 1683562768.283,
      "endTimestamp": 1683562769.06
    },
    {
      "id": "17670639",
      "positions": [
        [
          345,
          730
        ],
        [
          328,
          724
        ],
        [
          325,
          724
        ],
        [
          322,
          724
        ],
        [
          318,
          724
        ],
        [
          312,
          724
        ],
        [
          305,
          725
        ],
        [
          296,
          726
        ],
        [
          286,
          726
        ],
        [
          274,
          726
        ],
        [
          264,
          728
        ],
        [
          253,
          730
        ],
        [
          243,
          732
        ],
        [
          233,
          734
        ],
        [
          224,
          736
        ],
        [
          216,
          737
        ],
        [
          209,
          737
        ],
        [
          202,
          737
        ],
        [
          196,
          735
        ],
        [
          190,
          733
        ],
        [
          185,
          731
        ],
        [
          183,
          730
        ],
        [
          182,
          729
        ],
        [
          182,
          728
        ],
        [
          182,
          726
        ],
        [
          182,
          725
        ],
        [
          182,
          723
        ],
        [
          182,
          722
        ],
        [
          182,
          720
        ],
        [
          183,
          718
        ],
        [
          183,
          715
        ],
        [
          185,
          710
        ],
        [
          187,
          703
        ],
        [
          189,
          694
        ],
        [
          190,
          684
        ],
        [
          191,
          673
        ],
        [
          191,
          662
        ],
        [
          191,
          652
        ],
        [
          191,
          643
        ],
        [
          191,
          635
        ],
        [
          191,
          628
        ],
        [
          191,
          622
        ],
        [
          191,
          619
        ],
        [
          191,
          618
        ],
        [
          192,
          619
        ],
        [
          195,
          623
        ],
        [
          200,
          628
        ],
        [
          206,
          633
        ],
        [
          214,
          637
        ],
        [
          223,
          640
        ],
        [
          233,
          642
        ],
        [
          245,
          643
        ],
        [
          257,
          643
        ],
        [
          268,
          643
        ],
        [
          279,
          642
        ],
        [
          291,
          642
        ],
        [
          303,
          642
        ],
        [
          313,
          642
        ],
        [
          322,
          642
        ],
        [
          329,
          642
        ],
        [
          333,
          638
        ],
        [
          337,
          634
        ],
        [
          339,
          629
        ],
        [
          341,
          624
        ],
        [
          341,
          618
        ],
        [
          341,
          612
        ],
        [
          341,
          607
        ],
        [
          341,
          602
        ],
        [
          338,
          597
        ],
        [
          336,
          591
        ],
        [
          334,
          585
        ],
        [
          333,
          579
        ],
        [
          332,
          574
        ],
        [
          331,
          569
        ],
        [
          330,
          563
        ],
        [
          329,
          557
        ],
        [
          328,
          550
        ],
        [
          327,
          544
        ],
        [
          327,
          539
        ],
        [
          326,
          535
        ],
        [
          326,
          531
        ],
        [
          325,
          528
        ],
        [
          324,
          528
        ],
        [
          323,
          528
        ],
        [
          320,
          528
        ],
        [
          317,
          528
        ],
        [
          314,
          530
        ],
        [
          310,
          532
        ],
        [
          307,
          534
        ],
        [
          303,
          535
        ],
        [
          299,
          538
        ],
        [
          293,
          541
        ],
        [
          288,
          544
        ],
        [
          282,
          548
        ],
        [
          275,
          552
        ],
        [
          267,
          554
        ],
        [
          259,
          557
        ],
        [
          252,
          558
        ],
        [
          246,
          558
        ],
        [
          239,
          558
        ],
        [
          233,
          558
        ],
        [
          227,
          553
        ],
        [
          222,
          546
        ],
        [
          218,
          541
        ],
        [
          215,
          538
        ],
        [
          215,
          537
        ],
        [
          214,
          537
        ],
        [
          213,
          537
        ],
        [
          212,
          537
        ],
        [
          211,
          537
        ],
        [
          210,
          537
        ],
        [
          209,
          535
        ],
        [
          209,
          530
        ],
        [
          209,
          523
        ],
        [
          209,
          513
        ],
        [
          209,
          502
        ],
        [
          209,
          491
        ],
        [
          210,
          480
        ],
        [
          211,
          468
        ],
        [
          212,
          458
        ],
        [
          212,
          449
        ],
        [
          212,
          443
        ],
        [
          212,
          440
        ],
        [
          213,
          440
        ],
        [
          215,
          440
        ],
        [
          218,
          441
        ],
        [
          224,
          444
        ],
        [
          231,
          447
        ],
        [
          240,
          451
        ],
        [
          251,
          454
        ],
        [
          261,
          456
        ],
        [
          271,
          458
        ],
        [
          282,
          459
        ],
        [
          292,
          460
        ],
        [
          304,
          460
        ],
        [
          317,
          460
        ],
        [
          331,
          460
        ],
        [
          343,
          460
        ],
        [
          353,
          459
        ],
        [
          362,
          456
        ],
        [
          370,
          452
        ],
        [
          374,
          450
        ]
      ],
      "speeds": [
        112.67341691551874,
        214.2866485013624,
        176.46852911477617,
        235.29467203343478,
        374.99924004231923,
        415.9461454297661,
        532.6709690536208,
        624.9987334038653,
        705.8840161003043,
        599.8860620714491,
        657.6686017628485,
        637.3761475194168,
        599.8860620714491,
        542.3274223441003,
        503.89008810620925,
        411.7599012678111,
        411.76567605851085,
        372.03354246398817,
        395.2839064553152,
        316.775146785177,
        131.5337203525697,
        88.38816852457528,
        58.823668008358695,
        117.64733601671739,
        58.823668008358695,
        117.64568607651745,
        62.500804673064316,
        111.11033404858406,
        139.75396537423114,
        176.47100402507607,
        316.775146785177,
        455.00594598412783,
        542.3274223441003,
        591.1705470621129,
        649.719537414908,
        687.5088514037075,
        588.2284303825872,
        529.4130120752283,
        499.9989867230923,
        411.76567605851085,
        352.94200805015214,
        176.47100402507607,
        62.499873340386536,
        41.59461454297661,
        294.1183400417935,
        441.9408426228764,
        459.4275339979241,
        526.1275026533871,
        592.9258596829728,
        599.8860620714491,
        708.3307617941299,
        705.8840161003043,
        687.4986067442519,
        649.7286495074906,
        705.8840161003043,
        705.8840161003043,
        624.9987334038653,
        529.4130120752283,
        411.7599012678111,
        353.5579425115171,
        332.75224960819713,
        316.775146785177,
        316.775146785177,
        374.99924004231923,
        352.94200805015214,
        294.1183400417935,
        294.1183400417935,
        364.4337548817182,
        372.03354246398817,
        372.0283248949533,
        357.81040365594635,
        318.6880737597084,
        299.9430310357246,
        357.81040365594635,
        380.17188770328784,
        415.9461454297661,
        357.81040365594635,
        294.1183400417935,
        257.693579370139,
        235.29467203343478,
        186.01677123199408,
        62.499873340386536,
        58.823668008358695,
        176.46852911477617,
        176.47100402507607,
        225.34649803876843,
        263.0674407051394,
        212.09175121500795,
        242.53619648472935,
        312.4993667019327,
        394.60116105770913,
        342.99797843509003,
        424.17755348602356,
        503.89759675030695,
        485.0655900917384,
        502.5896397767317,
        441.9408426228764,
        352.94200805015214,
        437.49911338270573,
        352.94200805015214,
        459.4275339979241,
        506.02032560843105,
        376.6552543590248,
        265.1645055737258,
        58.823668008358695,
        58.822843038258725,
        30.303037308903853,
        58.823668008358695,
        58.823668008358695,
        58.823668008358695,
        139.75396537423114,
        294.1183400417935,
        411.76567605851085,
        624.9987334038653,
        647.0603480919457,
        647.0603480919457,
        649.719537414908,
        752.6093507213275,
        591.162256215217,
        529.4130120752283,
        374.99924004231923,
        176.47100402507607,
        58.823668008358695,
        117.64733601671739,
        197.6419532276576,
        394.60116105770913,
        447.9877088063253,
        579.3378165811821,
        712.6188153714929,
        599.8776489941735,
        599.8860620714491,
        649.7286495074906,
        628.1159534066941,
        705.8840161003043,
        764.707684108663,
        874.9982267654115,
        705.8840161003043,
        591.1705470621129,
        558.0503136959823,
        559.0158614969246,
        263.06375132669353
      ],
      "directions": [
        -2.8023000391357487,
        3.141592653589793,
        3.141592653589793,
        3.141592653589793,
        3.141592653589793,
        2.999695598985629,
        3.0309354324158977,
        3.141592653589793,
        3.141592653589793,
        2.9441970937399127,
        2.961739153797315,
        2.9441970937399127,
        2.9441970937399127,
        2.922923707715851,
        3.017237659043032,
        3.141592653589793,
        3.141592653589793,
        -2.819842099193151,
        -2.819842099193151,
        -2.761086276477428,
        -2.677945044588987,
        -2.356194490192345,
        -1.5707963267948966,
        -1.5707963267948966,
        -1.5707963267948966,
        -1.5707963267948966,
        -1.5707963267948966,
        -1.5707963267948966,
        -1.1071487177940904,
        -1.5707963267948966,
        -1.1902899496825317,
        -1.2924966677897853,
        -1.3521273809209546,
        -1.4711276743037347,
        -1.4801364395941514,
        -1.5707963267948966,
        -1.5707963267948966,
        -1.5707963267948966,
        -1.5707963267948966,
        -1.5707963267948966,
        -1.5707963267948966,
        -1.5707963267948966,
        -1.5707963267948966,
        0.7853981633974483,
        0.9272952180016122,
        0.7853981633974483,
        0.6947382761967031,
        0.4636476090008061,
        0.3217505543966422,
        0.19739555984988075,
        0.08314123188844123,
        0,
        0,
        -0.09065988720074511,
        0,
        0,
        0,
        0,
        0,
        -0.7853981633974483,
        -0.7853981633974483,
        -1.1902899496825317,
        -1.1902899496825317,
        -1.5707963267948966,
        -1.5707963267948966,
        -1.5707963267948966,
        -1.5707963267948966,
        -2.1112158270654806,
        -1.892546881191539,
        -1.892546881191539,
        -1.7359450042095235,
        -1.7681918866447774,
        -1.7681918866447774,
        -1.7359450042095235,
        -1.7359450042095235,
        -1.7126933813990606,
        -1.7359450042095235,
        -1.5707963267948966,
        -1.8157749899217608,
        -1.5707963267948966,
        -1.892546881191539,
        3.141592653589793,
        3.141592653589793,
        3.141592653589793,
        3.141592653589793,
        2.5535900500422257,
        2.677945044588987,
        2.5535900500422257,
        2.896613990462929,
        2.498091544796509,
        2.677945044588987,
        2.601173153319209,
        2.5535900500422257,
        2.62244653934327,
        2.896613990462929,
        2.782821983319221,
        2.999695598985629,
        3.141592653589793,
        3.141592653589793,
        3.141592653589793,
        -2.44685437739309,
        -2.191045812777718,
        -2.2455372690184494,
        -2.356194490192345,
        -1.5707963267948966,
        3.141592653589793,
        3.141592653589793,
        3.141592653589793,
        3.141592653589793,
        3.141592653589793,
        -2.0344439357957027,
        -1.5707963267948966,
        -1.5707963267948966,
        -1.5707963267948966,
        -1.5707963267948966,
        -1.5707963267948966,
        -1.4801364395941514,
        -1.4876550949064553,
        -1.4711276743037347,
        -1.5707963267948966,
        -1.5707963267948966,
        -1.5707963267948966,
        0,
        0,
        0.3217505543966422,
        0.4636476090008061,
        0.40489178628508343,
        0.4182243295792291,
        0.2662520491509254,
        0.19739555984988075,
        0.19739555984988075,
        0.09065988720074511,
        0.09966865249116202,
        0,
        0,
        0,
        0,
        -0.09966865249116202,
        -0.3217505543966422,
        -0.4636476090008061,
        -0.4636476090008061
      ],
      "startTimestamp": 1683562761.074,
      "endTimestamp": 1683562763.608
    },
    {
      "id": "17938188",
      "positions": [
        [
          323,
          543
        ]
      ],
      "speeds": [],
      "directions": [],
      "startTimestamp": 1683562774.171,
      "endTimestamp": 1683562774.264
    },
    {
      "id": "20002491",
      "positions": [
        [
          76,
          546
        ]
      ],
      "speeds": [],
      "directions": [],
      "startTimestamp": 1683562771.712,
      "endTimestamp": 1683562771.806
    },
    {
      "id": "42695569",
      "positions": [
        [
          196,
          723
        ],
        [
          201,
          722
        ],
        [
          203,
          722
        ],
        [
          207,
          723
        ],
        [
          211,
          725
        ],
        [
          214,
          727
        ],
        [
          216,
          728
        ],
        [
          217,
          728
        ],
        [
          219,
          728
        ],
        [
          223,
          726
        ],
        [
          228,
          724
        ],
        [
          235,
          723
        ],
        [
          244,
          722
        ],
        [
          254,
          722
        ],
        [
          266,
          722
        ],
        [
          279,
          722
        ],
        [
          290,
          723
        ],
        [
          300,
          723
        ],
        [
          309,
          723
        ],
        [
          317,
          723
        ],
        [
          326,
          723
        ],
        [
          331,
          722
        ],
        [
          335,
          721
        ],
        [
          337,
          720
        ],
        [
          338,
          720
        ],
        [
          341,
          719
        ],
        [
          343,
          718
        ],
        [
          346,
          717
        ],
        [
          348,
          716
        ],
        [
          349,
          715
        ],
        [
          350,
          714
        ],
        [
          351,
          713
        ],
        [
          351,
          712
        ],
        [
          351,
          711
        ],
        [
          351,
          710
        ],
        [
          351,
          709
        ],
        [
          352,
          709
        ]
      ],
      "speeds": [
        69.84962617883453,
        200.00019073504518,
        687.1794650699617,
        263.0674407051394,
        212.09175121500795,
        139.75396537423114,
        58.823668008358695,
        117.64733601671739,
        263.06375132669353,
        336.5771337429737,
        415.94031201024643,
        532.6709690536208,
        588.236680083587,
        749.9984800846385,
        764.707684108663,
        690.3336645730468,
        588.236680083587,
        529.4130120752283,
        470.58934406686956,
        529.4055873443285,
        318.69282264320606,
        242.5327950458692,
        131.5337203525697,
        58.823668008358695,
        197.6419532276576,
        131.5337203525697,
        186.01677123199408,
        131.5337203525697,
        88.38816852457528,
        83.18922908595322,
        83.18806240204928,
        62.500804673064316,
        58.822843038258725,
        58.823668008358695,
        62.499873340386536,
        9.901006552980945
      ],
      "directions": [
        -0.19739555984988075,
        0,
        0.24497866312686414,
        0.4636476090008061,
        0.5880026035475675,
        0.4636476090008061,
        0,
        0,
        -0.4636476090008061,
        -0.3805063771123649,
        -0.14189705460416394,
        -0.11065722117389565,
        0,
        0,
        0,
        0.09065988720074511,
        0,
        0,
        0,
        0,
        -0.19739555984988075,
        -0.24497866312686414,
        -0.4636476090008061,
        0,
        -0.3217505543966422,
        -0.4636476090008061,
        -0.3217505543966422,
        -0.4636476090008061,
        -0.7853981633974483,
        -0.7853981633974483,
        -0.7853981633974483,
        -1.5707963267948966,
        -1.5707963267948966,
        -1.5707963267948966,
        -1.5707963267948966,
        0
      ],
      "startTimestamp": 1683562779.743,
      "endTimestamp": 1683562780.485
    },
    {
      "id": "43115015",
      "positions": [
        [
          333,
          628
        ]
      ],
      "speeds": [],
      "directions": [],
      "startTimestamp": 1683562774.756,
      "endTimestamp": 1683562774.833
    },
    {
      "id": "51011843",
      "positions": [
        [
          196,
          725
        ]
      ],
      "speeds": [],
      "directions": [],
      "startTimestamp": 1683562782.368,
      "endTimestamp": 1683562782.461
    },
    {
      "id": "60441728",
      "positions": [
        [
          95,
          641
        ],
        [
          78,
          644
        ],
        [
          75,
          647
        ],
        [
          73,
          650
        ],
        [
          70,
          651
        ],
        [
          68,
          651
        ],
        [
          66,
          651
        ],
        [
          65,
          651
        ],
        [
          64,
          651
        ],
        [
          63,
          651
        ],
        [
          62,
          651
        ],
        [
          62,
          650
        ],
        [
          62,
          649
        ],
        [
          62,
          648
        ]
      ],
      "speeds": [
        138.10141201305655,
        249.56768725785963,
        225.34649803876843,
        186.01677123199408,
        117.64733601671739,
        124.99974668077307,
        58.823668008358695,
        58.823668008358695,
        20.000019073504518,
        58.823668008358695,
        58.822843038258725,
        30.303037308903853,
        14.92539267947249
      ],
      "directions": [
        2.9669204545815537,
        2.356194490192345,
        2.158798930342464,
        2.819842099193151,
        3.141592653589793,
        3.141592653589793,
        3.141592653589793,
        3.141592653589793,
        3.141592653589793,
        3.141592653589793,
        -1.5707963267948966,
        -1.5707963267948966,
        -1.5707963267948966
      ],
      "startTimestamp": 1683562769.186,
      "endTimestamp": 1683562769.646
    },
    {
      "id": "66836218",
      "positions": [
        [
          336,
          726
        ]
      ],
      "speeds": [],
      "directions": [],
      "startTimestamp": 1683562766.51,
      "endTimestamp": 1683562766.685
    },
    {
      "id": "69990294",
      "positions": [
        [
          206,
          706
        ],
        [
          203,
          707
        ],
        [
          203,
          706
        ],
        [
          203,
          705
        ],
        [
          203,
          704
        ],
        [
          202,
          703
        ],
        [
          202,
          702
        ],
        [
          201,
          701
        ],
        [
          201,
          700
        ],
        [
          200,
          699
        ],
        [
          199,
          698
        ],
        [
          199,
          697
        ],
        [
          199,
          696
        ],
        [
          199,
          694
        ],
        [
          199,
          690
        ],
        [
          200,
          684
        ],
        [
          202,
          677
        ],
        [
          203,
          670
        ],
        [
          205,
          664
        ],
        [
          206,
          658
        ],
        [
          208,
          652
        ],
        [
          210,
          646
        ],
        [
          211,
          640
        ],
        [
          212,
          634
        ],
        [
          212,
          629
        ],
        [
          212,
          625
        ],
        [
          212,
          623
        ],
        [
          212,
          621
        ],
        [
          212,
          619
        ],
        [
          212,
          617
        ],
        [
          211,
          615
        ],
        [
          210,
          612
        ],
        [
          209,
          611
        ],
        [
          209,
          609
        ],
        [
          209,
          608
        ],
        [
          209,
          607
        ],
        [
          209,
          606
        ],
        [
          209,
          604
        ],
        [
          209,
          602
        ],
        [
          209,
          599
        ],
        [
          207,
          595
        ],
        [
          204,
          590
        ],
        [
          201,
          585
        ],
        [
          199,
          580
        ],
        [
          198,
          575
        ],
        [
          197,
          570
        ],
        [
          197,
          566
        ],
        [
          197,
          562
        ],
        [
          197,
          559
        ],
        [
          197,
          556
        ],
        [
          200,
          553
        ],
        [
          202,
          549
        ],
        [
          203,
          546
        ],
        [
          204,
          543
        ],
        [
          204,
          539
        ],
        [
          204,
          536
        ],
        [
          204,
          534
        ],
        [
          204,
          531
        ],
        [
          203,
          528
        ],
        [
          202,
          526
        ],
        [
          201,
          524
        ],
        [
          199,
          522
        ],
        [
          199,
          520
        ],
        [
          198,
          517
        ],
        [
          197,
          515
        ],
        [
          197,
          512
        ],
        [
          196,
          509
        ],
        [
          196,
          504
        ],
        [
          195,
          499
        ],
        [
          194,
          493
        ],
        [
          193,
          486
        ],
        [
          191,
          478
        ],
        [
          189,
          470
        ],
        [
          187,
          464
        ],
        [
          185,
          457
        ],
        [
          183,
          450
        ],
        [
          182,
          445
        ],
        [
          182,
          439
        ],
        [
          182,
          434
        ],
        [
          182,
          428
        ],
        [
          182,
          422
        ],
        [
          182,
          414
        ],
        [
          183,
          408
        ],
        [
          185,
          401
        ],
        [
          188,
          395
        ],
        [
          191,
          391
        ],
        [
          193,
          387
        ],
        [
          197,
          384
        ],
        [
          201,
          382
        ],
        [
          205,
          380
        ],
        [
          211,
          377
        ],
        [
          217,
          374
        ],
        [
          224,
          370
        ],
        [
          232,
          365
        ]
      ],
      "speeds": [
        10.300581321456571,
        62.499873340386536,
        58.823668008358695,
        58.822843038258725,
        83.18922908595322,
        62.499873340386536,
        83.18922908595322,
        58.823668008358695,
        83.18922908595322,
        42.85496634334973,
        19.607797671918096,
        58.823668008358695,
        124.99974668077307,
        235.29467203343478,
        357.81040365594635,
        455.00594598412783,
        415.9461454297661,
        372.03354246398817,
        357.81040365594635,
        395.2839064553152,
        372.03354246398817,
        357.80538555873363,
        357.81040365594635,
        312.4993667019327,
        235.29467203343478,
        117.64733601671739,
        124.99974668077307,
        117.64733601671739,
        117.64733601671739,
        131.5337203525697,
        197.6419532276576,
        83.18922908595322,
        117.64568607651745,
        58.823668008358695,
        20.000019073504518,
        30.303037308903853,
        117.64733601671739,
        117.64733601671739,
        187.49962002115961,
        263.0674407051394,
        342.9931680741224,
        342.99797843509003,
        336.57211836301354,
        299.9430310357246,
        299.9430310357246,
        235.29467203343478,
        249.99949336154614,
        176.47100402507607,
        176.47100402507607,
        265.1645055737258,
        263.0674407051394,
        186.01677123199408,
        186.01416244747665,
        249.99949336154614,
        176.47100402507607,
        117.64733601671739,
        187.49962002115961,
        186.01677123199408,
        131.5337203525697,
        131.5337203525697,
        176.77633704915056,
        117.64733601671739,
        186.01677123199408,
        131.53187566334677,
        187.50241401919294,
        186.01416244747665,
        294.1183400417935,
        318.6880737597084,
        357.81040365594635,
        415.9461454297661,
        485.0723929694587,
        515.387158740278,
        372.03354246398817,
        428.2427671914062,
        428.236761318423,
        318.69282264320606,
        352.93705822955235,
        294.1183400417935,
        352.94200805015214,
        374.99924004231923,
        470.58934406686956,
        357.81040365594635,
        455.00594598412783,
        394.60116105770913,
        294.1183400417935,
        263.0674407051394,
        312.4993667019327,
        263.0674407051394,
        263.06375132669353,
        419.26189612269343,
        394.60116105770913,
        474.25157318373135,
        589.6226258491341
      ],
      "directions": [
        2.819842099193151,
        -1.5707963267948966,
        -1.5707963267948966,
        -1.5707963267948966,
        -2.356194490192345,
        -1.5707963267948966,
        -2.356194490192345,
        -1.5707963267948966,
        -2.356194490192345,
        -2.356194490192345,
        -1.5707963267948966,
        -1.5707963267948966,
        -1.5707963267948966,
        -1.5707963267948966,
        -1.4056476493802699,
        -1.2924966677897853,
        -1.4288992721907328,
        -1.2490457723982544,
        -1.4056476493802699,
        -1.2490457723982544,
        -1.2490457723982544,
        -1.4056476493802699,
        -1.4056476493802699,
        -1.5707963267948966,
        -1.5707963267948966,
        -1.5707963267948966,
        -1.5707963267948966,
        -1.5707963267948966,
        -1.5707963267948966,
        -2.0344439357957027,
        -1.892546881191539,
        -2.356194490192345,
        -1.5707963267948966,
        -1.5707963267948966,
        -1.5707963267948966,
        -1.5707963267948966,
        -1.5707963267948966,
        -1.5707963267948966,
        -1.5707963267948966,
        -2.0344439357957027,
        -2.1112158270654806,
        -2.1112158270654806,
        -1.9513027039072615,
        -1.7681918866447774,
        -1.7681918866447774,
        -1.5707963267948966,
        -1.5707963267948966,
        -1.5707963267948966,
        -1.5707963267948966,
        -0.7853981633974483,
        -1.1071487177940904,
        -1.2490457723982544,
        -1.2490457723982544,
        -1.5707963267948966,
        -1.5707963267948966,
        -1.5707963267948966,
        -1.5707963267948966,
        -1.892546881191539,
        -2.0344439357957027,
        -2.0344439357957027,
        -2.356194490192345,
        -1.5707963267948966,
        -1.892546881191539,
        -2.0344439357957027,
        -1.5707963267948966,
        -1.892546881191539,
        -1.5707963267948966,
        -1.7681918866447774,
        -1.7359450042095235,
        -1.7126933813990606,
        -1.8157749899217608,
        -1.8157749899217608,
        -1.892546881191539,
        -1.849095985800008,
        -1.849095985800008,
        -1.7681918866447774,
        -1.5707963267948966,
        -1.5707963267948966,
        -1.5707963267948966,
        -1.5707963267948966,
        -1.5707963267948966,
        -1.4056476493802699,
        -1.2924966677897853,
        -1.1071487177940904,
        -0.9272952180016122,
        -1.1071487177940904,
        -0.6435011087932844,
        -0.4636476090008061,
        -0.4636476090008061,
        -0.4636476090008061,
        -0.4636476090008061,
        -0.5191461142465229,
        -0.5585993153435624
      ],
      "startTimestamp": 1683562776.882,
      "endTimestamp": 1683562778.846
    },
    {
      "id": "71325612",
      "positions": [
        [
          67,
          731
        ]
      ],
      "speeds": [],
      "directions": [],
      "startTimestamp": 1683562769.972,
      "endTimestamp": 1683562770.099
    },
    {
      "id": "72759890",
      "positions": [
        [
          336,
          641
        ],
        [
          331,
          647
        ],
        [
          331,
          654
        ],
        [
          331,
          662
        ],
        [
          331,
          672
        ],
        [
          329,
          683
        ],
        [
          328,
          693
        ],
        [
          327,
          703
        ],
        [
          327,
          713
        ],
        [
          327,
          721
        ],
        [
          327,
          728
        ],
        [
          326,
          734
        ],
        [
          326,
          739
        ],
        [
          325,
          744
        ],
        [
          324,
          747
        ],
        [
          322,
          749
        ],
        [
          321,
          751
        ],
        [
          319,
          753
        ],
        [
          317,
          756
        ],
        [
          316,
          758
        ]
      ],
      "speeds": [
        106.9897886782261,
        411.7599012678111,
        470.58934406686956,
        624.9987334038653,
        657.6686017628485,
        591.1705470621129,
        591.1705470621129,
        624.9987334038653,
        470.58934406686956,
        437.49911338270573,
        357.81040365594635,
        294.1183400417935,
        299.9430310357246,
        186.01416244747665,
        176.77897125575856,
        131.53187566334677,
        166.37845817190643,
        212.09175121500795,
        139.75396537423114
      ],
      "directions": [
        2.2655346029916,
        1.5707963267948966,
        1.5707963267948966,
        1.5707963267948966,
        1.750649826587375,
        1.6704649792860586,
        1.6704649792860586,
        1.5707963267948966,
        1.5707963267948966,
        1.5707963267948966,
        1.7359450042095235,
        1.5707963267948966,
        1.7681918866447774,
        1.892546881191539,
        2.356194490192345,
        2.0344439357957027,
        2.356194490192345,
        2.158798930342464,
        2.0344439357957027
      ],
      "startTimestamp": 1683562780.813,
      "endTimestamp": 1683562781.188
    },
    {
      "id": "74517860",
      "positions": [
        [
          327,
          639
        ],
        [
          317,
          637
        ],
        [
          314,
          637
        ],
        [
          311,
          637
        ],
        [
          309,
          637
        ],
        [
          306,
          636
        ],
        [
          304,
          636
        ],
        [
          302,
          635
        ],
        [
          301,
          635
        ],
        [
          299,
          635
        ],
        [
          298,
          635
        ],
        [
          297,
          635
        ],
        [
          296,
          635
        ],
        [
          295,
          636
        ],
        [
          294,
          637
        ]
      ],
      "speeds": [
        53.114810871743835,
        187.49962002115961,
        176.47100402507607,
        117.64568607651745,
        197.64489836017873,
        117.64568607651745,
        131.5337203525697,
        62.499873340386536,
        117.64733601671739,
        58.823668008358695,
        62.499873340386536,
        58.823668008358695,
        83.18922908595322,
        83.18922908595322
      ],
      "directions": [
        -2.9441970937399127,
        3.141592653589793,
        3.141592653589793,
        3.141592653589793,
        -2.819842099193151,
        3.141592653589793,
        -2.677945044588987,
        3.141592653589793,
        3.141592653589793,
        3.141592653589793,
        3.141592653589793,
        3.141592653589793,
        2.356194490192345,
        2.356194490192345
      ],
      "startTimestamp": 1683562767.714,
      "endTimestamp": 1683562768.123
    },
    {
      "id": "75655788",
      "positions": [
        [
          321,
          472
        ]
      ],
      "speeds": [],
      "directions": [],
      "startTimestamp": 1683562773.418,
      "endTimestamp": 1683562773.479
    },
    {
      "id": "80900065",
      "positions": [
        [
          324,
          649
        ]
      ],
      "speeds": [],
      "directions": [],
      "startTimestamp": 1683562781.513,
      "endTimestamp": 1683562781.607
    },
    {
      "id": "87322953",
      "positions": [
        [
          81,
          465
        ]
      ],
      "speeds": [],
      "directions": [],
      "startTimestamp": 1683562772.266,
      "endTimestamp": 1683562772.325
    },
    {
      "id": "90571612",
      "positions": [
        [
          336,
          716
        ],
        [
          326,
          715
        ],
        [
          323,
          715
        ],
        [
          322,
          715
        ],
        [
          321,
          715
        ]
      ],
      "speeds": [
        245.11815358277946,
        176.47100402507607,
        62.499873340386536,
        58.823668008358695
      ],
      "directions": [
        -3.0419240010986313,
        3.141592653589793,
        3.141592653589793,
        3.141592653589793
      ],
      "startTimestamp": 1683562764.971,
      "endTimestamp": 1683562765.113
    },
    {
      "id": "94607395",
      "positions": [
        [
          325,
          720
        ]
      ],
      "speeds": [],
      "directions": [],
      "startTimestamp": 1683562775.543,
      "endTimestamp": 1683562775.62
    }
  ],
  "screenSize": [
    390,
    844
  ],
  "screenScale": 3
}